simple_util/DailyRotatingFileHandler.py
simple_util/__init__.py
simple_util/ckquery.py
simple_util/date_util.py
simple_util/delete_safe_list.py
simple_util/harbor_api.py
simple_util/id_generator.py
simple_util/slogger.py
simple_util/util.py
test/TestSnowflakeIDGenerator.py
test/__init__.py
simple_util-0.3.26.dist-info/METADATA
simple_util-0.3.26.dist-info/WHEEL
simple_util-0.3.26.dist-info/top_level.txt
simple_util-0.3.26.dist-info/RECORD
