Metadata-Version: 2.1
Name: simple_util
Version: 0.3.26
Summary: 封装了一些日常用的函数
Home-page: https://pypi.org/project/simple-util/
Author: Johnliu
Author-email: 1242108463@qq.com
License: MIT
Platform: UNKNOWN
Classifier: Development Status :: 3 - Alpha
Classifier: Intended Audience :: Developers
Classifier: License :: OSI Approved :: MIT License
Classifier: Programming Language :: Python
Classifier: Programming Language :: Python :: 3.7
